og/__init__.py
og/evaluator/EvaluatedAlgorithm.py
og/evaluator/EvaluationData.py
og/evaluator/Evaluator.py
og/evaluator/RecommenderMetrics.py
og/evaluator/__init__.py
og_evaluator/EvaluatedAlgorithm.py
og_evaluator/EvaluationData.py
og_evaluator/Evaluator.py
og_evaluator/RecommenderMetrics.py
og_evaluator/__init__.py
og_recsys_evaluator-0.0.4.dist-info/METADATA
og_recsys_evaluator-0.0.4.dist-info/WHEEL
og_recsys_evaluator-0.0.4.dist-info/top_level.txt
og_recsys_evaluator-0.0.4.dist-info/RECORD
