Metadata-Version: 2.1
Name: og-recsys-evaluator
Version: 0.0.4
Summary: Recsys Evaluator package
Author: OG
Author-email: blogphp.biz@gmail.com
License: UNKNOWN
Keywords: python,evaluator
Platform: UNKNOWN
Classifier: Development Status :: 3 - Alpha
Classifier: Intended Audience :: Education
Classifier: Programming Language :: Python :: 3
Classifier: Operating System :: MacOS :: MacOS X
Classifier: Operating System :: Microsoft :: Windows
Requires-Dist: surprise
